MANIFEST.in
README.txt
setup.py
NHL_API_Wrapper/__init__.py
NHL_API_Wrapper.egg-info/PKG-INFO
NHL_API_Wrapper.egg-info/SOURCES.txt
NHL_API_Wrapper.egg-info/dependency_links.txt
NHL_API_Wrapper.egg-info/requires.txt
NHL_API_Wrapper.egg-info/top_level.txt