Metadata-Version: 1.1
Name: NHL-API-Wrapper
Version: 0.6
Summary: A wrapper for the NHL API
Home-page: UNKNOWN
Author: Peter Faulkner
Author-email: faulknep@yahoo.com
License: MIT
Keywords: nhl,nhl api,nhl api wrapper,hockey,stats
Platform: UNKNOWN
Classifier: Development Status :: 5 - Production/Stable
Classifier: Intended Audience :: Education
Classifier: Operating System :: Microsoft :: Windows :: Windows 10
Classifier: License :: OSI Approved :: MIT License
Classifier: Programming Language :: Python :: 3
